README.rst
setup.py
NiceJuzi/__GetDate.py
NiceJuzi/__init__.py
NiceJuzi/__util.py
NiceJuzi.egg-info/PKG-INFO
NiceJuzi.egg-info/SOURCES.txt
NiceJuzi.egg-info/dependency_links.txt
NiceJuzi.egg-info/top_level.txt