Metadata-Version: 1.1
Name: NiceJuzi
Version: 1.0.1
Summary: <util function>
Home-page: https://gitee.com/juziweb/NiceJuzi.git
Author: <juzi>
Author-email: 2233987442@qq.com
License: BSD License
Platform: all
Classifier: Development Status :: 4 - Beta
Classifier: Operating System :: OS Independent
Classifier: Intended Audience :: Developers
Classifier: License :: OSI Approved :: BSD License
Classifier: Programming Language :: Python
Classifier: Programming Language :: Python :: Implementation
Classifier: Programming Language :: Python :: 2
Classifier: Programming Language :: Python :: 2.7
Classifier: Topic :: Software Development :: Libraries
